{
  "resourceType" : "PractitionerRole",
  "id" : "f1942bac-b8b3-45a1-b1d0-6928326d03ce",
  "meta" : {
    "profile" : ["http://fhir.nmdp.org/ig/matchsync/StructureDefinition/nmdp-practitioner-role"],
    "security" : [{
      "system" : "http://terminology.nmdp.org/codesystem/transplant-center",
      "code" : "tc_123"
    }]
  },
  "text" : {
    "status" : "generated",
    "div" : "<div xmlns=\"http://www.w3.org/1999/xhtml\"><p><b>Generated Narrative: PractitionerRole</b><a name=\"f1942bac-b8b3-45a1-b1d0-6928326d03ce\"> </a></p><div style=\"display: inline-block; background-color: #d9e0e7; padding: 6px; margin: 4px; border: 1px solid #8da1b4; border-radius: 5px; line-height: 60%\"><p style=\"margin-bottom: 0px\">Resource PractitionerRole &quot;f1942bac-b8b3-45a1-b1d0-6928326d03ce&quot; </p><p style=\"margin-bottom: 0px\">Profile: <a href=\"StructureDefinition-nmdp-practitioner-role.html\">NMDPPractitionerRole</a></p><p style=\"margin-bottom: 0px\">Security Labels: <span title=\"{http://terminology.nmdp.org/codesystem/transplant-center http://terminology.nmdp.org/codesystem/transplant-center}\">http://terminology.nmdp.org/codesystem/transplant-center</span></p></div><p><b>practitioner</b>: <a href=\"Bundle-BundleExample-Practitioner.html#urn-uuid-26b2e265-9a7a-4e5e-b99d-bb301e8a3bfa\">urn:uuid:26b2e265-9a7a-4e5e-b99d-bb301e8a3bfa: Lisa Simpson</a></p><p><b>code</b>: Referring Physician <span style=\"background: LightGoldenRodYellow; margin: 4px; border: 1px solid khaki\"> (<a href=\"CodeSystem-nmdp-practitioner-role-cs.html\">NMDP Practitioner Roles</a>#referringphysician)</span></p></div>"
  },
  "practitioner" : {
    "reference" : "urn:uuid:26b2e265-9a7a-4e5e-b99d-bb301e8a3bfa",
    "display" : "Lisa Simpson"
  },
  "code" : [{
    "coding" : [{
      "system" : "http://terminology.nmdp.org/codesystem/practitionerrole",
      "code" : "referringphysician",
      "display" : "Referring Physician"
    }]
  }]
}